hyper_rpc/__init__.py
hyper_rpc/hrpc.py
hyper_rpc-0.0.1a4.dist-info/entry_points.txt
hyper_rpc-0.0.1a4.dist-info/LICENSE
hyper_rpc-0.0.1a4.dist-info/WHEEL
hyper_rpc-0.0.1a4.dist-info/METADATA
hyper_rpc-0.0.1a4.dist-info/RECORD
