Metadata-Version: 2.1
Name: hyper-rpc
Version: 0.0.1a4
Summary: Simple RPC with Protobuf Services
Home-page: https://github.com/hyperpy/hyper-rpc
Author: decentral1se
Author-email: hi@decentral1.se
Maintainer: decentral1se
Maintainer-email: hi@decentral1.se
Requires-Python: >=3.6,<4.0
Classifier: Programming Language :: Python :: 3
Classifier: Programming Language :: Python :: 3.6
Classifier: Programming Language :: Python :: 3.7
Classifier: Programming Language :: Python :: 3.8
Requires-Dist: grpcio_tools (>=1.31.0,<2.0.0)
Requires-Dist: purerpc (>=0.6.1,<0.7.0)
Project-URL: Repository, https://github.com/hyperpy/hyper-rpc
